CrysFieldExplorer/CrysFieldExplorer.py
CrysFieldExplorer/Operators.py
CrysFieldExplorer/Optimization.py
CrysFieldExplorer/Test.py
CrysFieldExplorer/Visulization.py
CrysFieldExplorer/__init__.py
CrysFieldExplorer-1.0.11.dist-info/LICENSE
CrysFieldExplorer-1.0.11.dist-info/METADATA
CrysFieldExplorer-1.0.11.dist-info/WHEEL
CrysFieldExplorer-1.0.11.dist-info/top_level.txt
CrysFieldExplorer-1.0.11.dist-info/RECORD
